tomopal/__init__.py
tomopal/crtomopy/__init__.py
tomopal/crtomopy/crtomo/__init__.py
tomopal/crtomopy/crtomo/crc.py
tomopal/crtomopy/data/demo/demo_data.dat
tomopal/crtomopy/data/demo/demo_elecs.dat
tomopal/crtomopy/data/demo/demo_elevation.dat
tomopal/crtomopy/demo/pjt_demo.py
tomopal/crtomopy/ip/MtoPhase.cfg
tomopal/crtomopy/parent/__init__.py
tomopal/crtomopy/parent/inventory.py
tomopal/geoview/__init__.py
tomopal/geoview/diavatly.py
tomopal/geoview/iotomo.py
tomopal/model/__init__.py
tomopal/model/mohinh.py
tomopal/post/__init__.py
tomopal/post/analysis.py
tomopal/spatial/__init__.py
tomopal/spatial/transform.py
tomopal-1.0.19.dist-info/LICENSE
tomopal-1.0.19.dist-info/METADATA
tomopal-1.0.19.dist-info/WHEEL
tomopal-1.0.19.dist-info/top_level.txt
tomopal-1.0.19.dist-info/RECORD
